drf_braces/__init__.py
drf_braces/mixins.py
drf_braces/models.py
drf_braces/parsers.py
drf_braces/renderers.py
drf_braces/utils.py
drf_braces/fields/__init__.py
drf_braces/fields/_fields.py
drf_braces/fields/custom.py
drf_braces/fields/mixins.py
drf_braces/fields/modified.py
drf_braces/forms/__init__.py
drf_braces/forms/fields.py
drf_braces/forms/serializer_form.py
drf_braces/serializers/__init__.py
drf_braces/serializers/enforce_validation_serializer.py
drf_braces/serializers/form_serializer.py
drf_braces/serializers/swapping.py
drf_braces/tests/__init__.py
drf_braces/tests/test_mixins.py
drf_braces/tests/test_parsers.py
drf_braces/tests/test_renderers.py
drf_braces/tests/test_utils.py
drf_braces/tests/fields/__init__.py
drf_braces/tests/fields/test_custom.py
drf_braces/tests/fields/test_fields.py
drf_braces/tests/fields/test_mixins.py
drf_braces/tests/fields/test_modified.py
drf_braces/tests/forms/__init__.py
drf_braces/tests/forms/test_fields.py
drf_braces/tests/forms/test_serializer_form.py
drf_braces/tests/serializers/__init__.py
drf_braces/tests/serializers/test_enforce_validation_serializer.py
drf_braces/tests/serializers/test_form_serializer.py
drf_braces/tests/serializers/test_swapping.py
django_rest_framework_braces-0.3.4.dist-info/AUTHORS.rst
django_rest_framework_braces-0.3.4.dist-info/LICENSE.rst
django_rest_framework_braces-0.3.4.dist-info/METADATA
django_rest_framework_braces-0.3.4.dist-info/WHEEL
django_rest_framework_braces-0.3.4.dist-info/top_level.txt
django_rest_framework_braces-0.3.4.dist-info/RECORD
