Metadata-Version: 1.1
Name: django-rest-framework-braces
Version: 0.3.4
Summary: Collection of utilities for working with DRF
Home-page: https://github.com/dealertrack/django-rest-framework-braces
Author: Miroslav Shubernetskiy
Author-email: UNKNOWN
License: MIT
Keywords: django-rest-framework
Platform: UNKNOWN
Classifier: Intended Audience :: Developers
Classifier: Natural Language :: English
Classifier: License :: OSI Approved :: MIT License
Classifier: Programming Language :: Python
Classifier: Programming Language :: Python :: 2.7
Classifier: Programming Language :: Python :: 3
Classifier: Programming Language :: Python :: 3.4
Classifier: Programming Language :: Python :: 3.5
Classifier: Development Status :: 2 - Pre-Alpha
